odoo/addons/sale_order_line_cancel/README.rst
odoo/addons/sale_order_line_cancel/__init__.py
odoo/addons/sale_order_line_cancel/__manifest__.py
odoo/addons/sale_order_line_cancel/hooks.py
odoo/addons/sale_order_line_cancel/i18n/it.po
odoo/addons/sale_order_line_cancel/i18n/sale_order_line_cancel.pot
odoo/addons/sale_order_line_cancel/models/__init__.py
odoo/addons/sale_order_line_cancel/models/res_company.py
odoo/addons/sale_order_line_cancel/models/res_config_settings.py
odoo/addons/sale_order_line_cancel/models/sale_order.py
odoo/addons/sale_order_line_cancel/models/sale_order_line.py
odoo/addons/sale_order_line_cancel/readme/CONTRIBUTORS.rst
odoo/addons/sale_order_line_cancel/readme/DESCRIPTION.rst
odoo/addons/sale_order_line_cancel/security/sale_order_line_cancel.xml
odoo/addons/sale_order_line_cancel/static/description/icon.png
odoo/addons/sale_order_line_cancel/static/description/index.html
odoo/addons/sale_order_line_cancel/tests/__init__.py
odoo/addons/sale_order_line_cancel/tests/common.py
odoo/addons/sale_order_line_cancel/tests/test_sale_order_line_cancel.py
odoo/addons/sale_order_line_cancel/views/res_config_settings_views.xml
odoo/addons/sale_order_line_cancel/views/sale_order.xml
odoo/addons/sale_order_line_cancel/views/sale_order_line.xml
odoo/addons/sale_order_line_cancel/wizards/__init__.py
odoo/addons/sale_order_line_cancel/wizards/sale_order_line_cancel.py
odoo/addons/sale_order_line_cancel/wizards/sale_order_line_cancel.xml
odoo_addon_sale_order_line_cancel-16.0.2.0.0.1.dist-info/METADATA
odoo_addon_sale_order_line_cancel-16.0.2.0.0.1.dist-info/WHEEL
odoo_addon_sale_order_line_cancel-16.0.2.0.0.1.dist-info/top_level.txt
odoo_addon_sale_order_line_cancel-16.0.2.0.0.1.dist-info/RECORD
