Metadata-Version: 2.1
Name: odoo-addon-sale_order_line_cancel
Version: 16.0.2.0.0.1
Summary: Sale cancel remaining
Home-page: https://github.com/OCA/sale-workflow
Author: Okia, BCIM, Camptocamp, ACSONE SA/NV, MT Software, Odoo Community Association (OCA)
Author-email: support@odoo-community.org
License: AGPL-3
Classifier: Programming Language :: Python
Classifier: Framework :: Odoo
Classifier: Framework :: Odoo :: 16.0
Classifier: License :: OSI Approved :: GNU Affero General Public License v3
Requires-Python: >=3.10
Requires-Dist: odoo<16.1dev,>=16.0a
